chattool/__init__.py
chattool/const.py
chattool/core/__init__.py
chattool/core/chattype.py
chattool/core/request.py
chattool/core/response.py
chattool/fastobj/__init__.py
chattool/fastobj/basic.py
chattool/fastobj/capture.py
chattool/mcp/__init__.py
chattool/mcp/server.py
chattool/mcp/test_complete.py
chattool/mcp/aliyun/__init__.py
chattool/mcp/aliyun/config.py
chattool/mcp/aliyun/prompts.py
chattool/mcp/aliyun/resources.py
chattool/mcp/aliyun/tools.py
chattool/mcp/aliyun/utils.py
chattool/mcp/tests/__init__.py
chattool/mcp/tests/test_mcp_server.py
chattool/mcp/tests/usage_examples.py
chattool/tools/__init__.py
chattool/tools/githubclient.py
chattool/tools/interact.py
chattool/tools/zulipclient.py
chattool/tools/aliyun_dns/__init__.py
chattool/tools/aliyun_dns/client.py
chattool/tools/dns/__init__.py
chattool/tools/dns/dynamic_ip_updater.py
chattool/tools/dns/ssl_cert_updater.py
chattool/tools/dns/utils.py
chattool/tools/tencent_dns/__init__.py
chattool/tools/tencent_dns/client.py
chattool/utils/__init__.py
chattool/utils/basic.py
chattool/utils/custom_logger.py
chattool/utils/urltool.py
chattool-4.3.1.dist-info/LICENSE
chattool-4.3.1.dist-info/METADATA
chattool-4.3.1.dist-info/WHEEL
chattool-4.3.1.dist-info/entry_points.txt
chattool-4.3.1.dist-info/top_level.txt
chattool-4.3.1.dist-info/RECORD
