Metadata-Version: 2.1
Name: chattool
Version: 4.3.1
Summary: Toolkit for Chat API
Author-email: Rex Wang <1073853456@qq.com>
License: MIT license
Project-URL: Homepage, https://github.com/cubenlp/chattool
Project-URL: Repository, https://github.com/cubenlp/chattool
Keywords: chattool
Classifier: Development Status :: 2 - Pre-Alpha
Classifier: Intended Audience :: Developers
Classifier: License :: OSI Approved :: MIT License
Classifier: Natural Language :: English
Classifier: Programming Language :: Python :: 3.9
Classifier: Programming Language :: Python :: 3.10
Classifier: Programming Language :: Python :: 3.11
Classifier: Programming Language :: Python :: 3.12
Requires-Python: >=3.9
License-File: LICENSE
Requires-Dist: Click>=7.0
Requires-Dist: requests>=2.20
Requires-Dist: aiohttp>=3.8
Requires-Dist: tqdm>=4.60
Requires-Dist: python-dotenv>=0.17.0
Requires-Dist: loguru>=0.7
Requires-Dist: batch-executor>=0.3.0
Requires-Dist: colorama
Requires-Dist: fastapi
Requires-Dist: uvicorn
Requires-Dist: platformdirs>=3.0
Requires-Dist: pydantic>=2.0.0
Requires-Dist: httpx
Requires-Dist: PyGithub
Requires-Dist: filelock
Requires-Dist: fastmcp; python_version >= "3.10"
Provides-Extra: dev
Requires-Dist: wheel; extra == "dev"
Requires-Dist: coverage; extra == "dev"
Requires-Dist: twine; extra == "dev"
Requires-Dist: pytest>=3; extra == "dev"
Requires-Dist: pytest-asyncio; extra == "dev"
Requires-Dist: pytest-mock; extra == "dev"
Requires-Dist: alibabacloud-alidns20150109==3.5.10; extra == "dev"
Requires-Dist: alibabacloud-tea-openapi>=0.3.0; extra == "dev"
Requires-Dist: tencentcloud-sdk-python; extra == "dev"
Requires-Dist: dnspython; extra == "dev"
